{"type":"ContactFilter","currentStatus":"Active","depth":"complete","folderId":"1413","name":"20% split part1","permissions":["Retrieve","SetSecurity","Delete","Update"],"updatedAt":"1485170372","updatedBy":"55","criteria":[{"type":"ContactFieldCriterion","id":"-367804","condition":{"type":"TextValueCondition","operator":"endsWith","value":"0"},"fieldId":"100032"},{"type":"ContactFieldCriterion","id":"-367805","condition":{"type":"TextValueCondition","operator":"endsWith","value":"1"},"fieldId":"100032"}],"scope":"global","statement":"-367804 OR -367805"}