{"type":"ContactFilter","currentStatus":"Active","depth":"complete","folderId":"1469","name":"SYSTEM - Campaign - Received TLA email","permissions":["Retrieve","SetSecurity","Delete","Update"],"updatedAt":"1408354037","updatedBy":"27","criteria":[{"type":"EmailSentCriterion","id":"309282","activityRestriction":{"type":"NumericValueCondition","operator":"notLess","value":"1"},"timeRestriction":{"type":"DateValueCondition","operator":"withinLast","value":{"type":"RelativeDate","offset":"12","timePeriod":"month"}},"emailIds":["7228","7229","7227","7226","7230","7231","10003","10004"]}],"scope":"global"}