{"type":"ContactFilter","currentStatus":"Draft","depth":"complete","folderId":"1469","name":"SYSTEM - No call","permissions":["Retrieve","SetSecurity","Delete","Update"],"updatedAt":"1503912168","updatedBy":"58","criteria":[{"type":"ContactFieldCriterion","id":"46587","condition":{"type":"TextValueCondition","operator":"endsWith","value":"wolff-arzneimittel.de"},"fieldId":"100001"},{"type":"ContactFieldCriterion","id":"46588","condition":{"type":"TextValueCondition","operator":"contains","value":"August Wolff"},"fieldId":"100004"},{"type":"ContactFieldCriterion","id":"46589","condition":{"type":"TextValueCondition","operator":"contains","value":"Gtfmbh"},"fieldId":"100004"},{"type":"ContactFieldCriterion","id":"46590","condition":{"type":"TextValueCondition","operator":"matchesWildcardPattern","value":"*Borgwaldt**"},"fieldId":"100004"},{"type":"ContactFieldCriterion","id":"379013","condition":{"type":"TextValueCondition","operator":"equal","value":"sund.ku.dk"},"fieldId":"100461"},{"type":"ContactFieldCriterion","id":"379014","condition":{"type":"TextValueCondition","operator":"contains","value":"Blegdamsvej 3"},"fieldId":"100006"},{"type":"ContactFieldCriterion","id":"379015","condition":{"type":"TextValueCondition","operator":"equal","value":"Denmark"},"fieldId":"100012"},{"type":"ContactFieldCriterion","id":"379016","condition":{"type":"TextValueCondition","operator":"contains","value":"Institut For Cellulær Og Molekylær Medicin"},"fieldId":"100004"},{"type":"ContactFieldCriterion","id":"379017","condition":{"type":"TextValueCondition","operator":"contains","value":"Institut for cellulaer og molekylaer medicin"},"fieldId":"100004"}],"scope":"global"}